pyvosklivesubtitle/__init__.py
pyvosklivesubtitle/libgcc_s_seh-1.dll
pyvosklivesubtitle/libstdc++-6.dll
pyvosklivesubtitle/libvosk.dll
pyvosklivesubtitle/libwinpthread-1.dll
pyvosklivesubtitle-0.2.1.dist-info/METADATA
pyvosklivesubtitle-0.2.1.dist-info/WHEEL
pyvosklivesubtitle-0.2.1.dist-info/entry_points.txt
pyvosklivesubtitle-0.2.1.dist-info/top_level.txt
pyvosklivesubtitle-0.2.1.dist-info/RECORD
