Metadata-Version: 2.1
Name: pyvosklivesubtitle
Version: 0.2.1
Summary: A Python based desktop aplication that can RECOGNIZE any live streaming in 21 languages that supported by VOSK then TRANSLATE and display it as LIVE SUBTITLES
Home-page: https://github.com/botbahlul/pyvosklivesubtitle
Author: Bot Bahlul
Author-email: bot.bahlul@gmail.com
License: MIT License
Requires-Dist: pysimplegui (>=4.60.1)
Requires-Dist: sounddevice (>=0.4.4)
Requires-Dist: vosk (>=0.3.44)
Requires-Dist: requests (>=2.27.1)
Requires-Dist: httpx (>=0.13.3)
Requires-Dist: streamlink (>=5.3.1)
Requires-Dist: urllib3 (<3.0,>=1.26.0)
Requires-Dist: six (>=1.16.0)
Requires-Dist: pysrt (>=1.1.2)
Requires-Dist: tqdm (>=4.64.0)
Requires-Dist: pywin32 (>=306)
